Workbook
Name FID_1: [1]AGR_Fuels!$A$2

Sheet Cover
A16: TIMLEAF Model
A19: Document type: | B19: CCUS Technologies
A20: Sector(s): | B20: Cross-sector
A21: Purpose: | B21: Specify CCUS technologies
A23: Original developer(s): | B23: Andrew Smith (UCC, asmith@ucc.ie)
B24: Hannah Daly (UCC, h.daly@ucc.ie)
B25: Olexandr Balyk (UCC, olexandr.balyk@ucc.ie)
A26: Current maintainer(s): | B26: Weipeng Xie (UCC, weipeng.xie@ucc.ie)
B27: *This file is a simple version of DAC representation by Neha Jaggeshar (Neha.Jaggeshar@ucc.ie)
A29: Part of TIM version: | B29: 1
A30: Model repository: | B30: https://github.com/MaREI-EPMG/TIMES-Ireland-model
A31: Licence: | B31: CC BY-NC-SA 4.0 (unless specified otherwise)
B32: https://creativecommons.org/licenses/by-nc-sa/4.0/

Sheet DAC - simple version
B1: New Processes | G1: ~FI_T
B2: TechName | C2: *TechDesc | D2: Comm-IN-A | E2: Comm-IN | F2: Comm-OUT-A | G2: Comm-OUT | H2: Input~2020 | I2: Input~2030 | J2: Input~2040 | K2: Input~2050 | L2: CAP2ACT | M2: START | N2: LIFE | O2: EFF | P2: INVCOST~2020 | Q2: INVCOST~2025 | R2: INVCOST~2030 | S2: INVCOST~2035 | T2: INVCOST~2040 | U2: INVCOST~2045 | V2: INVCOST~2050 | W2: FIXOM~2020 | X2: FIXOM~2025 | Y2: FIXOM~2030 | Z2: FIXOM~2035 | AA2: FIXOM~2040 | AB2: FIXOM~2045 | AC2: FIXOM~2050 | AD2: VAROM~2020 | AE2: VAROM~2025 | AF2: VAROM~2030 | AG2: VAROM~2035 | AH2: VAROM~2040 | AI2: VAROM~2045 | AJ2: VAROM~2050
B3: \I:Technology Name | C3: Technology Description | D3: Auxiliary Input Commodity | E3: Input Commodity | F3: Auxiliary Output Commodity | G3: Output Commodity | L3: Capacity to Activity Factor | W3: Fixed O&M Cost
B4: =C21 -> L-DAC02 | C4: =D21 -> HIGH TEMPERATURE LIQUID ADSORBENT DAC - all electrified | E4: SYSCO2 | H4: 1 | L4: 1 | P4: =Sheet1!D14 -> 2.14 | Q4: =Sheet1!E14 -> 2.02 | R4: =Sheet1!F14 -> 1.89 | S4: =Sheet1!G14 -> 1.78 | T4: =Sheet1!H14 -> 1.66 | U4: =Sheet1!I14 -> 1.54 | V4: =Sheet1!J14 -> 1.42 | W4: =Sheet1!D15 -> 0.139 | X4: =Sheet1!E15 -> 0.127 | Y4: =Sheet1!F15 -> 0.114 | Z4: =Sheet1!G15 -> 0.101 | AA4: =Sheet1!H15 -> 0.089 | AB4: =Sheet1!I15 -> 0.076 | AC4: =Sheet1!J15 -> 0.063
D5: ELCC | H5: =Sheet1!D17 -> 0.013399211 | I5: =Sheet1!F17 -> 0.01150011 | J5: =Sheet1!H17 -> 0.010761571 | K5: =Sheet1!J17 -> 0.010413403
B10: ~FI_Comm
B11: Csets | C11: CommName | D11: CommDesc | E11: Unit | F11: LimType | G11: CTSLvl | H11: PeakTS | I11: Ctype
B12: \I: Commodity Set Membership | C12: Commodity Name | D12: Commodity Description | E12: Unit | F12: Balance Equ Type Override | G12: Timeslice Tracking Level | H12: Peak Monitoring | I12: Electricity Indicator
B17: ~FI_Process
B18: Sets | C18: TechName | D18: TechDesc | E18: Tact | F18: Tcap | G18: Tslvl | H18: PrimaryCG | I18: Vintage
B19: \I: Process Set Membership | C19: Technology Name | D19: Technology Description | E19: Activity Unit | F19: Capacity Unit | G19: Timeslice Operational Level | H19: Operational Commodity Group | I19: Vintage Tracking
B20: PRE | C20: SCO2DACS | D20: CO2 Backstop process | E20: kt | F20: kta
B21: PRE | C21: L-DAC02 | D21: HIGH TEMPERATURE LIQUID ADSORBENT DAC - all electrified | E21: kt | F21: kta | G21: DAYNITE | H21: SYSCO2

Sheet Sheet2
A1: New Processes | G1: ~FI_T
A2: TechName | B2: *TechDesc | C2: Comm-IN | D2: Comm-OUT | E2: Other_Indexes | F2: Year | G2: Curr | H2: START | I2: EFF | J2: IRE_PRICE | K2: Life | L2: CAP2ACT | M2: INVCOST | N2: FIXOM | O2: VAROM | P2: CEH | Q2: CHPR
A3: \I:Technology Name | B3: Technology Description | C3: Input Commodity | D3: Output Commodity | E3: Output Commodity | G3: Currency | H3: Starting Year | I3: Efficiency | J3: Import/export cost | K3: Lifetime of Process | L3: Capacity to Activity Factor | M3: Investment Cost | N3: Fixed O&M Cost | O3: Variable O&M Cost | P3: Ratio of electricity lost to output gained | Q3: Output to Power Ratio
A4: IMPH2G | B4: Import green H2 gaseous | D4: SUPH2GC | E4: IMP | F4: 2030 | G4: MEUR2020 | H4: 2035 | J4: 22 | L4: 1
D5: SUPH2GC | E5: IMP | F5: 2050 | G5: MEUR2020 | J5: 12
A8: ~FI_Comm
A9: Csets | B9: CommName | C9: CommDesc | D9: Unit | E9: LimType | F9: CTSLvl | G9: PeakTS | H9: Ctype
A10: \I: Commodity Set Membership | B10: Commodity Name | C10: Commodity Description | D10: Unit | E10: Balance Equ Type Override | F10: Timeslice Tracking Level | G10: Peak Monitoring | H10: Electricity Indicator
A15: ~FI_Process
A16: Sets | B16: TechName | C16: TechDesc | D16: Tact | E16: Tcap | F16: Tslvl | G16: PrimaryCG | H16: Vintage
A17: \I: Process Set Membership | B17: Technology Name | C17: Technology Description | D17: Activity Unit | E17: Capacity Unit | F17: Timeslice Operational Level | G17: Operational Commodity Group | H17: Vintage Tracking
A18: IMP | B18: IMPH2G | C18: Import green H2 gaseous | D18: PJ | E18: PJa

Sheet Sheet1
B2: Direct Air Capture | US-REGEN Documentation | E2: 1 EUR = 1.14 USD: | H2: 1 MMBtu/tCO₂=0.001055056 PJ/ktCO₂
B4: High temperature with heat provided by electricity
D6: 2020 | E6: 2025 | F6: 2030 | G6: 2035 | H6: 2040 | I6: 2045 | J6: 2050
B7: Capital cost | C7: USD per tCO2 | D7: 2440 | E7: 2300 | F7: 2160 | G7: 2030 | H7: 1890 | I7: 1750 | J7: 1620
B8: Fixed Cost | C8: USD per year per tCO2 | D8: 159 | E8: 145 | F8: 130 | G8: 115 | H8: 101 | I8: 86.2 | J8: 71.6
B9: Variable cost | C9: USD per tCO2 | D9: 0 | E9: 0 | F9: 0 | G9: 0 | H9: 0 | I9: 0 | J9: 0
B10: Electricity Input | C10: MMBtu per tCO2 | D10: 12.7 | E10: 11.1 | F10: 10.9 | G10: 10.4 | H10: 10.2 | I10: 9.99 | J10: 9.87
B12: Converting to TIMLEAF units
B14: Capital cost | C14: MEur/ktCO2 | D14: 2.14 | E14: 2.02 | F14: 1.89 | G14: 1.78 | H14: 1.66 | I14: 1.54 | J14: 1.42
B15: Fixed Cost | C15: Meuro per year per ktCO2 | D15: 0.139 | E15: 0.127 | F15: 0.114 | G15: 0.101 | H15: 0.089 | I15: 0.076 | J15: 0.063
B16: Variable cost | C16: Meur per ktCO2 | D16: 0 | E16: 0 | F16: 0 | G16: 0 | H16: 0 | I16: 0 | J16: 0
B17: Electricity Input | C17: PJ per ktCO2 | D17: =D10*0.001055056 -> 0.013399211 | E17: =E10*0.001055056 -> 0.011711122 | F17: =F10*0.001055056 -> 0.01150011 | G17: =G10*0.001055056 -> 0.010972582 | H17: =H10*0.001055056 -> 0.010761571 | I17: =I10*0.001055056 -> 0.010540009 | J17: =J10*0.001055056 -> 0.010413403
M19: Historical CO2 emissions
T20: CO2 | U20: CO2B
B21: For historical emissions | M21: 2000 | N21: 45176.28 | O21: =N21/1000 -> 45.17628 | S21: 2000 | T21: 45176.28 | U21: 5875.28
B22: Low temperature with heat from Elctricity | M22: 2001 | N22: 47530.83 | O22: =N22/1000 -> 47.53083 | S22: 2001 | T22: 47530.83 | U22: 5895.15
M23: 2002 | N23: 46007.24 | O23: =N23/1000 -> 46.00724 | S23: 2002 | T23: 46007.24 | U23: 5915.02
D24: 2020 | E24: 2025 | F24: 2030 | G24: 2035 | H24: 2040 | I24: 2045 | J24: 2050 | M24: 2003 | N24: 45610.25 | O24: =N24/1000 -> 45.61025 | S24: 2003 | T24: 45610.25 | U24: 5934.89
B25: Capital cost | C25: USD per tCO2 | D25: 2930 | E25: 2650 | F25: 2390 | G25: 2160 | H25: 1960 | I25: 1770 | J25: 1600 | M25: 2004 | N25: 46092.14 | O25: =N25/1000 -> 46.09214 | S25: 2004 | T25: 46092.14 | U25: 5954.76
B26: Fixed Cost | C26: USD per year per tCO2 | D26: 249 | E26: 128 | F26: 116 | G26: 89 | H26: 81.3 | I26: 72.6 | J26: 68.1 | M26: 2005 | N26: 48078.92 | O26: =N26/1000 -> 48.07892 | S26: 2005 | T26: 48078.92 | U26: 5974.63
B27: Variable cost | C27: USD per tCO2 | D27: 14.6 | E27: 7.52 | F27: 6.77 | G27: 5.22 | H27: 4.77 | I27: 4.26 | J27: 3.99 | M27: 2006 | N27: 47527.98 | O27: =N27/1000 -> 47.52798 | S27: 2006 | T27: 47527.98 | U27: 6026.2
B28: Electricity Input | C28: MMBtu per tCO2 | D28: 7.72 | E28: 6.79 | F28: 6.66 | G28: 6.33 | H28: 6.22 | I28: 6.09 | J28: 6.02 | M28: 2007 | N28: 47587.64 | O28: =N28/1000 -> 47.58764 | S28: 2007 | T28: 47587.64 | U28: 6077.77
M29: 2008 | N29: 47291.06 | O29: =N29/1000 -> 47.29106 | S29: 2008 | T29: 47291.06 | U29: 6129.34
M30: 2009 | N30: 42112.99 | O30: =N30/1000 -> 42.11299 | S30: 2009 | T30: 42112.99 | U30: 6180.91
B31: Capital cost | C31: MEur/ktCO2 | D31: =D25/(1.14*1000) -> 2.5701754 | E31: =E25/(1.14*1000) -> 2.3245614 | F31: =F25/(1.14*1000) -> 2.0964912 | G31: =G25/(1.14*1000) -> 1.8947368 | H31: =H25/(1.14*1000) -> 1.7192982 | I31: =I25/(1.14*1000) -> 1.5526316 | J31: =J25/(1.14*1000) -> 1.4035088 | M31: 2010 | N31: 41727.19 | O31: =N31/1000 -> 41.72719 | S31: 2010 | T31: 41727.19 | U31: 6232.47
B32: Fixed Cost | C32: Meuro per year per ktCO2 | D32: =D26/(1.14*1000) -> 0.21842105 | E32: =E26/(1.14*1000) -> 0.1122807 | F32: =F26/(1.14*1000) -> 0.10175439 | G32: =G26/(1.14*1000) -> 0.078070175 | H32: =H26/(1.14*1000) -> 0.071315789 | I32: =I26/(1.14*1000) -> 0.063684211 | J32: =J26/(1.14*1000) -> 0.059736842 | M32: 2011 | N32: 38036.48 | O32: =N32/1000 -> 38.03648 | S32: 2011 | T32: 38036.48 | U32: 5476.71
B33: Variable cost | C33: Meur per ktCO2 | D33: =D27/(1.14*1000) -> 0.012807018 | E33: =E27/(1.14*1000) -> 0.0065964912 | F33: =F27/(1.14*1000) -> 0.0059385965 | G33: =G27/(1.14*1000) -> 0.0045789474 | H33: =H27/(1.14*1000) -> 0.0041842105 | I33: =I27/(1.14*1000) -> 0.0037368421 | J33: =J27/(1.14*1000) -> 0.0035 | M33: 2012 | N33: 38180.93 | O33: =N33/1000 -> 38.18093 | S33: 2012 | T33: 38180.93 | U33: 4445.75
B34: Electricity Input | C34: PJ per ktCO2 | D34: =D28*0.001055056 -> 0.0081450323 | E34: =E28*0.001055056 -> 0.0071638302 | F34: =F28*0.001055056 -> 0.007026673 | G34: =G28*0.001055056 -> 0.0066785045 | H34: =H28*0.001055056 -> 0.0065624483 | I34: =I28*0.001055056 -> 0.006425291 | J34: =J28*0.001055056 -> 0.0063514371 | M34: 2013 | N34: 37232.24 | O34: =N34/1000 -> 37.23224 | S34: 2013 | T34: 37232.24 | U34: 4566.74
M35: 2014 | N35: 36850.08 | O35: =N35/1000 -> 36.85008 | S35: 2014 | T35: 36850.08 | U35: 5927.31
M36: 2015 | N36: 38626 | O36: =N36/1000 -> 38.626 | S36: 2015 | T36: 38626 | U36: 5569.36
M37: 2016 | N37: 40091.69 | O37: =N37/1000 -> 40.09169 | S37: 2016 | T37: 40091.69 | U37: 4976.06
M38: 2017 | N38: 39070.96 | O38: =N38/1000 -> 39.07096 | S38: 2017 | T38: 39070.96 | U38: 6475.34
M39: 2018 | N39: 39132.59 | O39: =N39/1000 -> 39.13259 | Q39: =SUM(N21:N39) -> 811963.49 | S39: 2018 | T39: 39132.59 | U39: 4778.38
M40: 2019 | N40: 37215.8 | O40: =N40/1000 -> 37.2158 | Q40: =SUM(N21:N40) -> 849179.29 | S40: 2019 | T40: 37215.8 | U40: 4435.55
M41: 2020 | N41: 35128 | O41: =N41/1000 -> 35.128 | Q41: =SUM(N21:N41) -> 884307.29 | S41: 2020 | T41: 35128 | U41: 1513.71
N42: =SUM(N21:N41) -> 884307.29 | O42: =N42/1000 -> 884.30729 | S42: 2021 | T42: 36978 | U42: 856.67
T43: =SUM(T21:T42) -> 921285.29 | U43: =SUM(U21:U42) -> 115218 | W43: =T43+U43 -> 1036503.3
N45: =1300+884 -> 2184
