Workbook
Name Euro_GBP: #REF!
Name TransportCHi: [1]TransportCost_Inputs!$D$59:$AD$74
Name TransportCLo: [1]TransportCost_Inputs!$D$15:$AD$30
Name TransportCMe: [1]TransportCost_Inputs!$D$37:$AD$52
Name TransportInclude: [1]PickLists!$D$19
Name Years: [1]PickLists!$G$9:$G$34

Sheet Cover
A16: TIMES-Ireland Model
A19: Document type: | B19: Scenario
A20: Sector(s): | B20: Supply (SUP) and Agriculture (AGR) sectors
A21: Purpose: | B21: Specify fuel delivery cost
A23: Original developer(s): | B23: Alessandro Chiodi (UCC, a.chiodi@ucc.ie)
B24: James Glynn (UCC, james.glynn@ucc.ie)
A26: Current maintainer(s): | B26: Olexandr Balyk (UCC, olexandr.balyk@ucc.ie)
B27: Neha Jaggeshar (UCC, Neha.Jaggeshar@ucc.ie)
A29: Part of TIM version: | B29: 1
A30: Model repository: | B30: https://github.com/MaREI-EPMG/TIMES-Ireland-model
A31: Licence: | B31: CC BY-NC-SA 4.0 (unless specified otherwise)
B32: https://creativecommons.org/licenses/by-nc-sa/4.0/

Sheet Delivery cost
B1: Bioenergy delivery costs (€/GJ) | S1: Energy crops - Delivery Cost
S2: Source: Clancy et al., The economic viability of biomass crops versus conventional agricultural systems and its potential impact on farm incomes in Ireland, Energy Policy 2012
B3: ~TFM_INS-TS | U3: Transport and Processing | W3: Full Adder
B4: Pset_PN | C4: *Description | D4: Attribute | E4: Cset_CN | F4: CURR | G4: *Unit | H4: 2010 | I4: 2015 | J4: 2020 | K4: 2025 | L4: 2030 | M4: 2035 | N4: 2040 | O4: 2045 | P4: 2050 | Q4: 0 | S4: Miscanthus/Willow | T4: €(11)/GJ | U4: 0.53 | V4: 1.91 | W4: 2.41
B5: ABIOFRSR* | C5: Forest thinnings | D5: FLO_DELIV | E5: BIOWOO | F5: MEUR2011 | G5: €/GJ | H5: =SUM('Delivery cost'!$U$5:$W$5)*1.2 -> 4.5241269 | I5: =(SUM('Delivery cost'!$U$5:$V$5)+'Delivery cost'!$W$5*'Delivery cost'!F$31/'Delivery cost'!$E$31)*1.2 -> 4.1398412 | J5: =(SUM('Delivery cost'!$U$5:$V$5)+'Delivery cost'!$W$5*'Delivery cost'!G$31/'Delivery cost'!$E$31)*1.2 -> 3.7994739 | K5: =(SUM('Delivery cost'!$U$5:$V$5)+'Delivery cost'!$W$5*'Delivery cost'!H$31/'Delivery cost'!$E$31)*1.2 -> 4.0300453 | L5: =(SUM('Delivery cost'!$U$5:$V$5)+'Delivery cost'!$W$5*'Delivery cost'!I$31/'Delivery cost'!$E$31)*1.2 -> 4.1535657 | M5: =(SUM('Delivery cost'!$U$5:$V$5)+'Delivery cost'!$W$5*'Delivery cost'!J$31/'Delivery cost'!$E$31)*1.2 -> 4.2770861 | N5: =(SUM('Delivery cost'!$U$5:$V$5)+'Delivery cost'!$W$5*'Delivery cost'!K$31/'Delivery cost'!$E$31)*1.2 -> 4.3759024 | O5: =(SUM('Delivery cost'!$U$5:$V$5)+'Delivery cost'!$W$5*'Delivery cost'!L$31/'Delivery cost'!$E$31)*1.2 -> 4.3759024 | P5: =(SUM('Delivery cost'!$U$5:$V$5)+'Delivery cost'!$W$5*'Delivery cost'!M$31/'Delivery cost'!$E$31)*1.2 -> 4.3759024 | Q5: 5 | T5: €(00)/GJ | U5: =U4*Conversions!$C$7/Conversions!$C$18 -> 0.41199094 | V5: =V4*Conversions!$C$7/Conversions!$C$18 -> 1.4847221 | W5: =W4*Conversions!$C$7/Conversions!$C$18 -> 1.8733928
B6: MINBIOWOO1* | C6: Sawmill residues | D6: FLO_DELIV | E6: BIOWOO1 | F6: MEUR2011 | G6: €/GJ | H6: =SUM('Delivery cost'!$U$5:$W$5)*1.1 -> 4.1471163 | I6: =(SUM('Delivery cost'!$U$5:$V$5)+'Delivery cost'!$W$5*'Delivery cost'!F$31/'Delivery cost'!$E$31)*1.1 -> 3.7948545 | J6: =(SUM('Delivery cost'!$U$5:$V$5)+'Delivery cost'!$W$5*'Delivery cost'!G$31/'Delivery cost'!$E$31)*1.1 -> 3.4828511 | K6: =(SUM('Delivery cost'!$U$5:$V$5)+'Delivery cost'!$W$5*'Delivery cost'!H$31/'Delivery cost'!$E$31)*1.1 -> 3.6942082 | L6: =(SUM('Delivery cost'!$U$5:$V$5)+'Delivery cost'!$W$5*'Delivery cost'!I$31/'Delivery cost'!$E$31)*1.1 -> 3.8074352 | M6: =(SUM('Delivery cost'!$U$5:$V$5)+'Delivery cost'!$W$5*'Delivery cost'!J$31/'Delivery cost'!$E$31)*1.1 -> 3.9206623 | N6: =(SUM('Delivery cost'!$U$5:$V$5)+'Delivery cost'!$W$5*'Delivery cost'!K$31/'Delivery cost'!$E$31)*1.1 -> 4.0112439 | O6: =(SUM('Delivery cost'!$U$5:$V$5)+'Delivery cost'!$W$5*'Delivery cost'!L$31/'Delivery cost'!$E$31)*1.1 -> 4.0112439 | P6: =(SUM('Delivery cost'!$U$5:$V$5)+'Delivery cost'!$W$5*'Delivery cost'!M$31/'Delivery cost'!$E$31)*1.1 -> 4.0112439 | Q6: 5
B7: MINBIOWOO2* | C7: PCRW | D7: FLO_DELIV | E7: BIOWOO2 | F7: MEUR2011 | G7: €/GJ | H7: =SUM('Delivery cost'!$U$5:$W$5)*1.1 -> 4.1471163 | I7: =(SUM('Delivery cost'!$U$5:$V$5)+'Delivery cost'!$W$5*'Delivery cost'!F$31/'Delivery cost'!$E$31)*1.1 -> 3.7948545 | J7: =(SUM('Delivery cost'!$U$5:$V$5)+'Delivery cost'!$W$5*'Delivery cost'!G$31/'Delivery cost'!$E$31)*1.1 -> 3.4828511 | K7: =(SUM('Delivery cost'!$U$5:$V$5)+'Delivery cost'!$W$5*'Delivery cost'!H$31/'Delivery cost'!$E$31)*1.1 -> 3.6942082 | L7: =(SUM('Delivery cost'!$U$5:$V$5)+'Delivery cost'!$W$5*'Delivery cost'!I$31/'Delivery cost'!$E$31)*1.1 -> 3.8074352 | M7: =(SUM('Delivery cost'!$U$5:$V$5)+'Delivery cost'!$W$5*'Delivery cost'!J$31/'Delivery cost'!$E$31)*1.1 -> 3.9206623 | N7: =(SUM('Delivery cost'!$U$5:$V$5)+'Delivery cost'!$W$5*'Delivery cost'!K$31/'Delivery cost'!$E$31)*1.1 -> 4.0112439 | O7: =(SUM('Delivery cost'!$U$5:$V$5)+'Delivery cost'!$W$5*'Delivery cost'!L$31/'Delivery cost'!$E$31)*1.1 -> 4.0112439 | P7: =(SUM('Delivery cost'!$U$5:$V$5)+'Delivery cost'!$W$5*'Delivery cost'!M$31/'Delivery cost'!$E$31)*1.1 -> 4.0112439 | Q7: 5
B8: MINBIOMSW1* | C8: Solid BMSW | D8: FLO_DELIV | E8: BIOMSW1 | F8: MEUR2011 | G8: €/GJ | H8: 0 | I8: 0 | J8: 0 | K8: 0 | L8: 0 | M8: 0 | N8: 0 | O8: 0 | P8: 0 | Q8: 5
B9: MINBIOTLW* | C9: Tallow | D9: FLO_DELIV | E9: BIOTLW | F9: MEUR2011 | G9: €/GJ | H9: =SUM('Delivery cost'!$U$5:$W$5)*1.1 -> 4.1471163 | I9: =(SUM('Delivery cost'!$U$5:$V$5)+'Delivery cost'!$W$5*'Delivery cost'!F$31/'Delivery cost'!$E$31)*1.1 -> 3.7948545 | J9: =(SUM('Delivery cost'!$U$5:$V$5)+'Delivery cost'!$W$5*'Delivery cost'!G$31/'Delivery cost'!$E$31)*1.1 -> 3.4828511 | K9: =(SUM('Delivery cost'!$U$5:$V$5)+'Delivery cost'!$W$5*'Delivery cost'!H$31/'Delivery cost'!$E$31)*1.1 -> 3.6942082 | L9: =(SUM('Delivery cost'!$U$5:$V$5)+'Delivery cost'!$W$5*'Delivery cost'!I$31/'Delivery cost'!$E$31)*1.1 -> 3.8074352 | M9: =(SUM('Delivery cost'!$U$5:$V$5)+'Delivery cost'!$W$5*'Delivery cost'!J$31/'Delivery cost'!$E$31)*1.1 -> 3.9206623 | N9: =(SUM('Delivery cost'!$U$5:$V$5)+'Delivery cost'!$W$5*'Delivery cost'!K$31/'Delivery cost'!$E$31)*1.1 -> 4.0112439 | O9: =(SUM('Delivery cost'!$U$5:$V$5)+'Delivery cost'!$W$5*'Delivery cost'!L$31/'Delivery cost'!$E$31)*1.1 -> 4.0112439 | P9: =(SUM('Delivery cost'!$U$5:$V$5)+'Delivery cost'!$W$5*'Delivery cost'!M$31/'Delivery cost'!$E$31)*1.1 -> 4.0112439 | Q9: 5
B10: MINBIORVO* | C10: RVO | D10: FLO_DELIV | E10: BIORVO | F10: MEUR2011 | G10: €/GJ | H10: 0 | I10: 0 | J10: 0 | K10: 0 | L10: 0 | M10: 0 | N10: 0 | O10: 0 | P10: 0 | Q10: 5
B11: MINBIOWOO3* | C11: Straw | D11: FLO_DELIV | E11: BIOWOO3 | F11: MEUR2011 | G11: €/GJ | H11: =SUM('Delivery cost'!$U$5:$W$5)*1.1 -> 4.1471163 | I11: =(SUM('Delivery cost'!$U$5:$V$5)+'Delivery cost'!$W$5*'Delivery cost'!F$31/'Delivery cost'!$E$31)*1.1 -> 3.7948545 | J11: =(SUM('Delivery cost'!$U$5:$V$5)+'Delivery cost'!$W$5*'Delivery cost'!G$31/'Delivery cost'!$E$31)*1.1 -> 3.4828511 | K11: =(SUM('Delivery cost'!$U$5:$V$5)+'Delivery cost'!$W$5*'Delivery cost'!H$31/'Delivery cost'!$E$31)*1.1 -> 3.6942082 | L11: =(SUM('Delivery cost'!$U$5:$V$5)+'Delivery cost'!$W$5*'Delivery cost'!I$31/'Delivery cost'!$E$31)*1.1 -> 3.8074352 | M11: =(SUM('Delivery cost'!$U$5:$V$5)+'Delivery cost'!$W$5*'Delivery cost'!J$31/'Delivery cost'!$E$31)*1.1 -> 3.9206623 | N11: =(SUM('Delivery cost'!$U$5:$V$5)+'Delivery cost'!$W$5*'Delivery cost'!K$31/'Delivery cost'!$E$31)*1.1 -> 4.0112439 | O11: =(SUM('Delivery cost'!$U$5:$V$5)+'Delivery cost'!$W$5*'Delivery cost'!L$31/'Delivery cost'!$E$31)*1.1 -> 4.0112439 | P11: =(SUM('Delivery cost'!$U$5:$V$5)+'Delivery cost'!$W$5*'Delivery cost'!M$31/'Delivery cost'!$E$31)*1.1 -> 4.0112439 | Q11: 5
B12: ADGSCAT101 | C12: Cattle waste | D12: FLO_DELIV | E12: AGRBGS | F12: MEUR2011 | G12: €/GJ | H12: =SUM('Delivery cost'!$U$5:$W$5)*1.1 -> 4.1471163 | I12: =(SUM('Delivery cost'!$U$5:$V$5)+'Delivery cost'!$W$5*'Delivery cost'!F$31/'Delivery cost'!$E$31)*1.1 -> 3.7948545 | J12: =(SUM('Delivery cost'!$U$5:$V$5)+'Delivery cost'!$W$5*'Delivery cost'!G$31/'Delivery cost'!$E$31)*1.1 -> 3.4828511 | K12: =(SUM('Delivery cost'!$U$5:$V$5)+'Delivery cost'!$W$5*'Delivery cost'!H$31/'Delivery cost'!$E$31)*1.1 -> 3.6942082 | L12: =(SUM('Delivery cost'!$U$5:$V$5)+'Delivery cost'!$W$5*'Delivery cost'!I$31/'Delivery cost'!$E$31)*1.1 -> 3.8074352 | M12: =(SUM('Delivery cost'!$U$5:$V$5)+'Delivery cost'!$W$5*'Delivery cost'!J$31/'Delivery cost'!$E$31)*1.1 -> 3.9206623 | N12: =(SUM('Delivery cost'!$U$5:$V$5)+'Delivery cost'!$W$5*'Delivery cost'!K$31/'Delivery cost'!$E$31)*1.1 -> 4.0112439 | O12: =(SUM('Delivery cost'!$U$5:$V$5)+'Delivery cost'!$W$5*'Delivery cost'!L$31/'Delivery cost'!$E$31)*1.1 -> 4.0112439 | P12: =(SUM('Delivery cost'!$U$5:$V$5)+'Delivery cost'!$W$5*'Delivery cost'!M$31/'Delivery cost'!$E$31)*1.1 -> 4.0112439 | Q12: 5
B13: ADGSPIG101 | C13: Pig waste | D13: FLO_DELIV | E13: AGRBGS | F13: MEUR2011 | G13: €/GJ | H13: =SUM('Delivery cost'!$U$5:$W$5)*1.1 -> 4.1471163 | I13: =(SUM('Delivery cost'!$U$5:$V$5)+'Delivery cost'!$W$5*'Delivery cost'!F$31/'Delivery cost'!$E$31)*1.1 -> 3.7948545 | J13: =(SUM('Delivery cost'!$U$5:$V$5)+'Delivery cost'!$W$5*'Delivery cost'!G$31/'Delivery cost'!$E$31)*1.1 -> 3.4828511 | K13: =(SUM('Delivery cost'!$U$5:$V$5)+'Delivery cost'!$W$5*'Delivery cost'!H$31/'Delivery cost'!$E$31)*1.1 -> 3.6942082 | L13: =(SUM('Delivery cost'!$U$5:$V$5)+'Delivery cost'!$W$5*'Delivery cost'!I$31/'Delivery cost'!$E$31)*1.1 -> 3.8074352 | M13: =(SUM('Delivery cost'!$U$5:$V$5)+'Delivery cost'!$W$5*'Delivery cost'!J$31/'Delivery cost'!$E$31)*1.1 -> 3.9206623 | N13: =(SUM('Delivery cost'!$U$5:$V$5)+'Delivery cost'!$W$5*'Delivery cost'!K$31/'Delivery cost'!$E$31)*1.1 -> 4.0112439 | O13: =(SUM('Delivery cost'!$U$5:$V$5)+'Delivery cost'!$W$5*'Delivery cost'!L$31/'Delivery cost'!$E$31)*1.1 -> 4.0112439 | P13: =(SUM('Delivery cost'!$U$5:$V$5)+'Delivery cost'!$W$5*'Delivery cost'!M$31/'Delivery cost'!$E$31)*1.1 -> 4.0112439 | Q13: 5
B14: MINBIOMSW2* | C14: BMSW | D14: FLO_DELIV | E14: BIOMSW2 | F14: MEUR2011 | G14: €/GJ | H14: 0 | I14: 0 | J14: 0 | K14: 0 | L14: 0 | M14: 0 | N14: 0 | O14: 0 | P14: 0 | Q14: 5
B15: ABIOCRP4* | C15: Willow | D15: FLO_DELIV | E15: BIOWOO | F15: MEUR2011 | G15: €/GJ | H15: =SUM('Delivery cost'!$U$5:$W$5) -> 3.7701058 | I15: =(SUM('Delivery cost'!$U$5:$V$5)+'Delivery cost'!$W$5*'Delivery cost'!F$31/'Delivery cost'!$E$31) -> 3.4498677 | J15: =(SUM('Delivery cost'!$U$5:$V$5)+'Delivery cost'!$W$5*'Delivery cost'!G$31/'Delivery cost'!$E$31) -> 3.1662282 | K15: =(SUM('Delivery cost'!$U$5:$V$5)+'Delivery cost'!$W$5*'Delivery cost'!H$31/'Delivery cost'!$E$31) -> 3.3583711 | L15: =(SUM('Delivery cost'!$U$5:$V$5)+'Delivery cost'!$W$5*'Delivery cost'!I$31/'Delivery cost'!$E$31) -> 3.4613048 | M15: =(SUM('Delivery cost'!$U$5:$V$5)+'Delivery cost'!$W$5*'Delivery cost'!J$31/'Delivery cost'!$E$31) -> 3.5642384 | N15: =(SUM('Delivery cost'!$U$5:$V$5)+'Delivery cost'!$W$5*'Delivery cost'!K$31/'Delivery cost'!$E$31) -> 3.6465854 | O15: =(SUM('Delivery cost'!$U$5:$V$5)+'Delivery cost'!$W$5*'Delivery cost'!L$31/'Delivery cost'!$E$31) -> 3.6465854 | P15: =(SUM('Delivery cost'!$U$5:$V$5)+'Delivery cost'!$W$5*'Delivery cost'!M$31/'Delivery cost'!$E$31) -> 3.6465854 | Q15: 5
B16: ABIOCRP3* | C16: Miscanthus | D16: FLO_DELIV | E16: BIOWOO | F16: MEUR2011 | G16: €/GJ | H16: =SUM('Delivery cost'!$U$5:$W$5) -> 3.7701058 | I16: =(SUM('Delivery cost'!$U$5:$V$5)+'Delivery cost'!$W$5*'Delivery cost'!F$31/'Delivery cost'!$E$31) -> 3.4498677 | J16: =(SUM('Delivery cost'!$U$5:$V$5)+'Delivery cost'!$W$5*'Delivery cost'!G$31/'Delivery cost'!$E$31) -> 3.1662282 | K16: =(SUM('Delivery cost'!$U$5:$V$5)+'Delivery cost'!$W$5*'Delivery cost'!H$31/'Delivery cost'!$E$31) -> 3.3583711 | L16: =(SUM('Delivery cost'!$U$5:$V$5)+'Delivery cost'!$W$5*'Delivery cost'!I$31/'Delivery cost'!$E$31) -> 3.4613048 | M16: =(SUM('Delivery cost'!$U$5:$V$5)+'Delivery cost'!$W$5*'Delivery cost'!J$31/'Delivery cost'!$E$31) -> 3.5642384 | N16: =(SUM('Delivery cost'!$U$5:$V$5)+'Delivery cost'!$W$5*'Delivery cost'!K$31/'Delivery cost'!$E$31) -> 3.6465854 | O16: =(SUM('Delivery cost'!$U$5:$V$5)+'Delivery cost'!$W$5*'Delivery cost'!L$31/'Delivery cost'!$E$31) -> 3.6465854 | P16: =(SUM('Delivery cost'!$U$5:$V$5)+'Delivery cost'!$W$5*'Delivery cost'!M$31/'Delivery cost'!$E$31) -> 3.6465854 | Q16: 5
B17: ABIOCRP1* | C17: Wheat | D17: FLO_DELIV | E17: BIOWHE | F17: MEUR2011 | G17: €/GJ | H17: 0 | I17: 0 | J17: 0 | K17: 0 | L17: 0 | M17: 0 | N17: 0 | O17: 0 | P17: 0 | Q17: 5
B18: ABIOCRP2* | C18: OSR | D18: FLO_DELIV | E18: BIOOSR | F18: MEUR2011 | G18: €/GJ | H18: 0 | I18: 0 | J18: 0 | K18: 0 | L18: 0 | M18: 0 | N18: 0 | O18: 0 | P18: 0 | Q18: 5
B19: ABIOGAS1* | C19: Crops Anaerobic | D19: FLO_DELIV | E19: BIOGRA | F19: MEUR2011 | G19: €/GJ | H19: =SUM('Delivery cost'!$U$5:$W$5) -> 3.7701058 | I19: =(SUM('Delivery cost'!$U$5:$V$5)+'Delivery cost'!$W$5*'Delivery cost'!F$31/'Delivery cost'!$E$31) -> 3.4498677 | J19: =(SUM('Delivery cost'!$U$5:$V$5)+'Delivery cost'!$W$5*'Delivery cost'!G$31/'Delivery cost'!$E$31) -> 3.1662282 | K19: =(SUM('Delivery cost'!$U$5:$V$5)+'Delivery cost'!$W$5*'Delivery cost'!H$31/'Delivery cost'!$E$31) -> 3.3583711 | L19: =(SUM('Delivery cost'!$U$5:$V$5)+'Delivery cost'!$W$5*'Delivery cost'!I$31/'Delivery cost'!$E$31) -> 3.4613048 | M19: =(SUM('Delivery cost'!$U$5:$V$5)+'Delivery cost'!$W$5*'Delivery cost'!J$31/'Delivery cost'!$E$31) -> 3.5642384 | N19: =(SUM('Delivery cost'!$U$5:$V$5)+'Delivery cost'!$W$5*'Delivery cost'!K$31/'Delivery cost'!$E$31) -> 3.6465854 | O19: =(SUM('Delivery cost'!$U$5:$V$5)+'Delivery cost'!$W$5*'Delivery cost'!L$31/'Delivery cost'!$E$31) -> 3.6465854 | P19: =(SUM('Delivery cost'!$U$5:$V$5)+'Delivery cost'!$W$5*'Delivery cost'!M$31/'Delivery cost'!$E$31) -> 3.6465854 | Q19: 5
B20: MINBIOINDF* | C20: Industrial Food | D20: FLO_DELIV | E20: BIOINDF | F20: MEUR2011 | G20: €/GJ | H20: =SUM('Delivery cost'!$U$5:$W$5)*1.1 -> 4.1471163 | I20: =(SUM('Delivery cost'!$U$5:$V$5)+'Delivery cost'!$W$5*'Delivery cost'!F$31/'Delivery cost'!$E$31)*1.1 -> 3.7948545 | J20: =(SUM('Delivery cost'!$U$5:$V$5)+'Delivery cost'!$W$5*'Delivery cost'!G$31/'Delivery cost'!$E$31)*1.1 -> 3.4828511 | K20: =(SUM('Delivery cost'!$U$5:$V$5)+'Delivery cost'!$W$5*'Delivery cost'!H$31/'Delivery cost'!$E$31)*1.1 -> 3.6942082 | L20: =(SUM('Delivery cost'!$U$5:$V$5)+'Delivery cost'!$W$5*'Delivery cost'!I$31/'Delivery cost'!$E$31)*1.1 -> 3.8074352 | M20: =(SUM('Delivery cost'!$U$5:$V$5)+'Delivery cost'!$W$5*'Delivery cost'!J$31/'Delivery cost'!$E$31)*1.1 -> 3.9206623 | N20: =(SUM('Delivery cost'!$U$5:$V$5)+'Delivery cost'!$W$5*'Delivery cost'!K$31/'Delivery cost'!$E$31)*1.1 -> 4.0112439 | O20: =(SUM('Delivery cost'!$U$5:$V$5)+'Delivery cost'!$W$5*'Delivery cost'!L$31/'Delivery cost'!$E$31)*1.1 -> 4.0112439 | P20: =(SUM('Delivery cost'!$U$5:$V$5)+'Delivery cost'!$W$5*'Delivery cost'!M$31/'Delivery cost'!$E$31)*1.1 -> 4.0112439 | Q20: 5
B21: BIOWPE_Domestic | C21: Donestic WPE production | D21: FLO_DELIV | E21: BIOWPE | F21: MEUR2011 | G21: €/GJ | H21: =SUM('Delivery cost'!$U$5:$W$5)*1.1 -> 4.1471163 | I21: =(SUM('Delivery cost'!$U$5:$V$5)+'Delivery cost'!$W$5*'Delivery cost'!F$31/'Delivery cost'!$E$31)*1.1 -> 3.7948545 | J21: =(SUM('Delivery cost'!$U$5:$V$5)+'Delivery cost'!$W$5*'Delivery cost'!G$31/'Delivery cost'!$E$31)*1.1 -> 3.4828511 | K21: =(SUM('Delivery cost'!$U$5:$V$5)+'Delivery cost'!$W$5*'Delivery cost'!H$31/'Delivery cost'!$E$31)*1.1 -> 3.6942082 | L21: =(SUM('Delivery cost'!$U$5:$V$5)+'Delivery cost'!$W$5*'Delivery cost'!I$31/'Delivery cost'!$E$31)*1.1 -> 3.8074352 | M21: =(SUM('Delivery cost'!$U$5:$V$5)+'Delivery cost'!$W$5*'Delivery cost'!J$31/'Delivery cost'!$E$31)*1.1 -> 3.9206623 | N21: =(SUM('Delivery cost'!$U$5:$V$5)+'Delivery cost'!$W$5*'Delivery cost'!K$31/'Delivery cost'!$E$31)*1.1 -> 4.0112439 | O21: =(SUM('Delivery cost'!$U$5:$V$5)+'Delivery cost'!$W$5*'Delivery cost'!L$31/'Delivery cost'!$E$31)*1.1 -> 4.0112439 | P21: =(SUM('Delivery cost'!$U$5:$V$5)+'Delivery cost'!$W$5*'Delivery cost'!M$31/'Delivery cost'!$E$31)*1.1 -> 4.0112439 | Q21: 5
B22: ADGSPOU101 | C22: Poultry waste | D22: FLO_DELIV | E22: AGRBGS | F22: MEUR2011 | G22: €/GJ | H22: =AVERAGE(H12,H13) -> 4.1471163 | I22: =AVERAGE(I12,I13) -> 3.7948545 | J22: =AVERAGE(J12,J13) -> 3.4828511 | K22: =AVERAGE(K12,K13) -> 3.6942082 | L22: =AVERAGE(L12,L13) -> 3.8074352 | M22: =AVERAGE(M12,M13) -> 3.9206623 | N22: =AVERAGE(N12,N13) -> 4.0112439 | O22: =AVERAGE(O12,O13) -> 4.0112439 | P22: =AVERAGE(P12,P13) -> 4.0112439 | Q22: 5
B24: unit: €/GJ
B29: From: WEO 2020 | H29: Stated Policies
E30: 2010 | F30: 2015 | G30: 2020 | H30: 2025 | I30: 2030 | J30: 2035 | K30: 2040 | L30: 2045 | M30: 2050
C31: IEA crude oil imports | E31: 91 | F31: =(E43-D43)/($E$42-$D$42)*($F$30-$D$42)+D43 -> 75.444444 | G31: =(E43-F43)/($F$42-$E$42)*($G$30-$E$42)+E43 -> 61.666667 | H31: 71 | I31: 76 | J31: 81 | K31: 85 | L31: =K31 -> 85 | M31: =L31 -> 85 | N31: $2019/barrel
C32: Natural Gas imports-Europe | E32: 8.7 | F32: =(E44-D44)/($E$42-$D$42)*($F$30-$D$42)+D44 -> 7.5888889 | G32: =(E44-F44)/($F$42-$E$42)*($G$30-$E$42)+E44 -> 6.6 | H32: 7.3 | I32: 11.1 | J32: 13 | K32: =J32*(1+(J32/I32-1)) -> 15.225225 | L32: =K32 -> 15.225225 | M32: =L32 -> 15.225225 | N32: $2019/MBtu
C33: OECD steam coal imports | E33: 108 | F33: =(E45-D45)/($E$42-$D$42)*($F$30-$D$42)+D45 -> 81.888889 | G33: =(E45-F45)/($F$42-$E$42)*($G$30-$E$42)+E45 -> 60.333333 | H33: 65 | I33: 80 | J33: 88 | K33: =J33*(1+(J33/I33-1)) -> 96.8 | L33: =K33 -> 96.8 | M33: =L33 -> 96.8 | N33: $2019/tonne
B34: Growth | C34: IEA crude oil imports | F34: =F31/E31 -> 0.82905983 | G34: =G31/F31 -> 0.8173785 | H34: =H31/G31 -> 1.1513514 | I34: =I31/H31 -> 1.0704225 | J34: =J31/I31 -> 1.0657895 | K34: =K31/J31 -> 1.0493827 | L34: =L31/K31 -> 1 | M34: =M31/L31 -> 1
B35: Growth | C35: Natural Gas imports-Europe | F35: =F32/E32 -> 0.87228608 | G35: =G32/F32 -> 0.86969253 | H35: =H32/G32 -> 1.1060606 | I35: =I32/H32 -> 1.5205479 | J35: =J32/I32 -> 1.1711712 | K35: =K32/J32 -> 1.1711712 | L35: =L32/K32 -> 1 | M35: =M32/L32 -> 1
B36: Growth | C36: OECD steam coal imports | F36: =F33/E33 -> 0.75823045 | G36: =G33/F33 -> 0.73677069 | H36: =H33/G33 -> 1.0773481 | I36: =I33/H33 -> 1.2307692 | J36: =J33/I33 -> 1.1 | K36: =K33/J33 -> 1.1 | L36: =L33/K33 -> 1 | M36: =M33/L33 -> 1
B41: Fossil fuels import prices | F41: Stated Policies
B42: Real Terms (2019 Prices) | C42: unit | D42: 2010 | E42: 2019 | F42: 2025 | G42: 2030 | H42: 2035 | I42: 2040
B43: IEA crude oil | C43: $2019/barrel | D43: 91 | E43: 63 | F43: 71 | G43: 76 | H43: 81 | I43: 85
B44: Natural Gas - EU | C44: $2019/MBtu | D44: 8.7 | E44: 6.7 | F44: 7.3 | G44: 11.1 | H44: 13 | I44: =H44*(1+(H44/G44-1)) -> 15.225225
B45: Steam coal - EU | C45: $2019/tonne | D45: 108 | E45: 61 | F45: 65 | G45: 80 | H45: 88 | I45: =H45*(1+(H45/G45-1)) -> 96.8
B46: Source: Table 2.2 - Fossil fuel prices by scenario - WEO 2020, IEA

Sheet Conversions
A2: ktoe to PJ | B2: 0.041868
A3: toe to GJ | B3: 41.868
A5: EU-28
B6: Euro inflation rate | C6: € CPI | F6: Consumer Price Index (CPI) - CSO
A7: 2000 | C7: 100 | F7: Base=100 | G7: 2000 | H7: 2010 | I7: 2005 | J7: 2006
A8: 2001 | B8: 0.022 | C8: =C7+(C7*B8) -> 102.2 | F8: 39052 | G8: 79.3 | H8: 101.2 | I8: 94.3 | J8: 100
A9: 2002 | B9: 0.021 | C9: =C8+(C8*B9) -> 104.3462 | F9: 38687 | G9: =G8/$I$8*100 -> 84.093319 | H9: =H8/$I$8*100 -> 107.31707 | I9: =I8/$I$8*100 -> 100 | J9: =J8/$I$8*100 -> 106.04454
A10: 2003 | B10: 0.02 | C10: =C9+(C9*B10) -> 106.43312 | F10: 36861 | G10: =G8/$G$8*100 -> 100 | H10: =H8/$G$8*100 -> 127.61665 | I10: =I8/$G$8*100 -> 118.91551 | J10: =J8/$G$8*100 -> 126.1034
A11: 2004 | B11: 0.023 | C11: =C10+(C10*B11) -> 108.88109 | F11: 40878 | G11: 76 | H11: 96.9 | I11: 90.3 | J11: 93.9
A12: 2005 | B12: 0.023 | C12: =C11+(C11*B12) -> 111.38535 | F12: Source: http://www.cso.ie/px/pxeirestat/Statire/SelectVarVal/Define.asp?maintable=CPA04&PLanguage=0
A13: 2006 | B13: 0.023 | C13: =C12+(C12*B13) -> 113.94721
A14: 2007 | B14: 0.024 | C14: =C13+(C13*B14) -> 116.68195
A15: 2008 | B15: 0.037 | C15: =C14+(C14*B15) -> 120.99918
A16: 2009 | B16: 0.01 | C16: =C15+(C15*B16) -> 122.20917
A17: 2010 | B17: 0.021 | C17: =C16+(C16*B17) -> 124.77556
A18: 2011 | B18: 0.031 | C18: =C17+(C17*B18) -> 128.64361 | E18: =C7/C18 -> 0.77734139
A19: 2012 | B19: 0.026 | C19: =C18+(C18*B19) -> 131.98834
A20: 2013 | B20: 0.015 | C20: =C19+(C19*B20) -> 133.96816
A21: 2014 | B21: 0.005 | C21: =C20+(C20*B21) -> 134.63801
A22: 2015 | B22: 0 | C22: =C21+(C21*B22) -> 134.63801
A23: Source: Eurostat
